{
  "main_topic": "Linear Algebra Fundamentals: Vectors, Matrices, Transformations, and Eigenvalues",
  "description": "An introductory series on the fundamental concepts of linear algebra, focusing on vectors, matrices, transformations, and eigenvalues, tailored for high school students.",
  "total_subtopics": 8,
  "difficulty": "beginner",
  "audience": "high school students",
  "subtopics": [
    {
      "title": "Introduction to Vectors",
      "order_index": 1,
      "estimated_duration": 2.0,
      "difficulty": "beginner",
      "prerequisites": [],
      "key_points": [
        "Definition of a vector",
        "Representation of vectors in 2D and 3D",
        "Types of vectors: zero vector, unit vector"
      ]
    },
    {
      "title": "Vector Operations",
      "order_index": 2,
      "estimated_duration": 3.0,
      "difficulty": "beginner",
      "prerequisites": [
        "Introduction to Vectors"
      ],
      "key_points": [
        "Addition and subtraction of vectors",
        "Scalar multiplication",
        "Dot product of vectors"
      ]
    },
    {
      "title": "Introduction to Matrices",
      "order_index": 3,
      "estimated_duration": 2.0,
      "difficulty": "beginner",
      "prerequisites": [
        "Introduction to Vectors"
      ],
      "key_points": [
        "Definition of a matrix",
        "Types of matrices: row, column, square",
        "Matrix notation and dimensions"
      ]
    },
    {
      "title": "Matrix Operations",
      "order_index": 4,
      "estimated_duration": 3.0,
      "difficulty": "intermediate",
      "prerequisites": [
        "Introduction to Matrices"
      ],
      "key_points": [
        "Addition and subtraction of matrices",
        "Scalar multiplication of matrices",
        "Matrix multiplication basics"
      ]
    },
    {
      "title": "Determinants and Inverses",
      "order_index": 5,
      "estimated_duration": 4.0,
      "difficulty": "intermediate",
      "prerequisites": [
        "Matrix Operations"
      ],
      "key_points": [
        "Definition of the determinant",
        "Calculating the determinant of 2x2 and 3x3 matrices",
        "Finding the inverse of a matrix"
      ]
    },
    {
      "title": "Linear Transformations",
      "order_index": 6,
      "estimated_duration": 5.0,
      "difficulty": "intermediate",
      "prerequisites": [
        "Matrix Operations",
        "Determinants and Inverses"
      ],
      "key_points": [
        "Definition of linear transformations",
        "Matrix representation of transformations",
        "Examples of transformations in geometry"
      ]
    },
    {
      "title": "Introduction to Eigenvalues and Eigenvectors",
      "order_index": 7,
      "estimated_duration": 4.0,
      "difficulty": "advanced",
      "prerequisites": [
        "Determinants and Inverses",
        "Linear Transformations"
      ],
      "key_points": [
        "Definition of eigenvalues and eigenvectors",
        "Characteristic polynomial",
        "Finding eigenvalues and eigenvectors for 2x2 matrices"
      ]
    },
    {
      "title": "Applications of Eigenvalues",
      "order_index": 8,
      "estimated_duration": 3.0,
      "difficulty": "advanced",
      "prerequisites": [
        "Introduction to Eigenvalues and Eigenvectors"
      ],
      "key_points": [
        "Real-world applications of eigenvalues",
        "Role in systems of differential equations",
        "Importance in data science and machine learning"
      ]
    }
  ]
}